gcpy/FirestoreTriggerFunction.py
gcpy/PubSubTriggerFunction.py
gcpy/__init__.py
gcpy/firestore/Collection.py
gcpy/firestore/Document.py
gcpy/firestore/Types.py
gcpy/firestore/__init__.py
gcpy/functions/BinaryPayload.py
gcpy/functions/CloudFunction.py
gcpy/functions/HTTPFunction.py
gcpy/functions/Types.py
gcpy/functions/__init__.py
gcpy/generators/__init__.py
gcpy/generators/collection_class.py
gcpy/generators/deploy.py
gcpy/generators/main_py_generator.py
gcpy/queues/__init__.py
gcpy/tests/__init__.py
gcpy/tests/main.py
gcpy/utils/__init__.py
gcpy/utils/answer.py
gcpy/utils/binary.py
gcpy-0.1.4.dist-info/LICENSE
gcpy-0.1.4.dist-info/WHEEL
gcpy-0.1.4.dist-info/METADATA
gcpy-0.1.4.dist-info/RECORD
