Metadata-Version: 2.1
Name: gcpy
Version: 0.1.4
Summary: Google Cloud Platform (GCP) Python helpers for functions, queues, collections and more
License: MIT
Author: Maxim Bazarov
Author-email: bazaroffma@gmail.com
Requires-Python: >=3.7,<4.0
Classifier: License :: OSI Approved :: MIT License
Classifier: Programming Language :: Python :: 3
Classifier: Programming Language :: Python :: 3.7
Classifier: Programming Language :: Python :: 3.8
Requires-Dist: google.api_core (>=1.21.0,<2.0.0)
Requires-Dist: google.cloud (>=0.34.0,<0.35.0)
